{"openapi":"3.1.0","info":{"title":"Basic Health Information System API","description":"API for managing health programs.","version":"0.3.0"},"paths":{"/api/v1/auth/signup":{"post":{"tags":["Auth"],"summary":"Doctor Signup","operationId":"doctor_signup_api_v1_auth_signup_post","requestBody":{"content":{"application/json":{"schema":{"$ref":"#/components/schemas/DoctorSignUp"}}},"required":true},"responses":{"201":{"description":"Successful Response","content":{"application/json":{"schema":{}}}},"422":{"description":"Validation Error","content":{"application/json":{"schema":{"$ref":"#/components/schemas/HTTPValidationError"}}}}}}},"/api/v1/auth/login":{"post":{"tags":["Auth"],"summary":"Doctor Login","operationId":"doctor_login_api_v1_auth_login_post","requestBody":{"content":{"application/json":{"schema":{"$ref":"#/components/schemas/DoctorLogin"}}},"required":true},"responses":{"200":{"description":"Successful Response","content":{"application/json":{"schema":{"$ref":"#/components/schemas/TokenResponse"}}}},"422":{"description":"Validation Error","content":{"application/json":{"schema":{"$ref":"#/components/schemas/HTTPValidationError"}}}}}}},"/api/v1/auth/profile":{"get":{"tags":["Auth"],"summary":"Get Current Doctor Profile","description":"Endpoint to retrieve the doctor's profile.","operationId":"doctor_profile_api_v1_auth_profile_get","parameters":[{"name":"authorization","in":"header","required":true,"schema":{"type":"string","title":"Authorization"}}],"responses":{"200":{"description":"Successful Response","content":{"application/json":{"schema":{"$ref":"#/components/schemas/DoctorProfile"}}}},"422":{"description":"Validation Error","content":{"application/json":{"schema":{"$ref":"#/components/schemas/HTTPValidationError"}}}}}}},"/api/v1/programs/":{"post":{"tags":["Programs"],"summary":"Create Program","operationId":"create_program_api_v1_programs__post","requestBody":{"required":true,"content":{"application/json":{"schema":{"$ref":"#/components/schemas/ProgramCreate"}}}},"responses":{"201":{"description":"Successful Response","content":{"application/json":{"schema":{"$ref":"#/components/schemas/app__programs__schemas__Program"}}}},"422":{"description":"Validation Error","content":{"application/json":{"schema":{"$ref":"#/components/schemas/HTTPValidationError"}}}}}},"get":{"tags":["Programs"],"summary":"List Programs","operationId":"list_programs_api_v1_programs__get","parameters":[{"name":"skip","in":"query","required":false,"schema":{"type":"integer","default":0,"title":"Skip"}},{"name":"limit","in":"query","required":false,"schema":{"type":"integer","default":10,"title":"Limit"}}],"responses":{"200":{"description":"Successful Response","content":{"application/json":{"schema":{"type":"array","items":{"$ref":"#/components/schemas/app__programs__schemas__Program"},"title":"Response List Programs Api V1 Programs  Get"}}}},"422":{"description":"Validation Error","content":{"application/json":{"schema":{"$ref":"#/components/schemas/HTTPValidationError"}}}}}}},"/api/v1/clients/":{"post":{"tags":["Clients"],"summary":"Register Client","operationId":"register_client_api_v1_clients__post","requestBody":{"required":true,"content":{"application/json":{"schema":{"$ref":"#/components/schemas/ClientCreate"}}}},"responses":{"201":{"description":"Successful Response","content":{"application/json":{"schema":{"$ref":"#/components/schemas/app__clients__schemas__Client"}}}},"422":{"description":"Validation Error","content":{"application/json":{"schema":{"$ref":"#/components/schemas/HTTPValidationError"}}}}}},"get":{"tags":["Clients"],"summary":"List All Clients","description":"Retrieves a list of all registered clients with optional pagination.","operationId":"list_all_clients_api_v1_clients__get","parameters":[{"name":"skip","in":"query","required":false,"schema":{"type":"integer","description":"Number of clients to skip","default":0,"title":"Skip"},"description":"Number of clients to skip"},{"name":"limit","in":"query","required":false,"schema":{"type":"integer","description":"Maximum number of clients to retrieve","default":100,"title":"Limit"},"description":"Maximum number of clients to retrieve"}],"responses":{"200":{"description":"Successful Response","content":{"application/json":{"schema":{"type":"array","items":{"$ref":"#/components/schemas/app__clients__schemas__Client"},"title":"Response List All Clients Api V1 Clients  Get"}}}},"422":{"description":"Validation Error","content":{"application/json":{"schema":{"$ref":"#/components/schemas/HTTPValidationError"}}}}}}},"/api/v1/clients/{client_id}":{"get":{"tags":["Clients"],"summary":"Get Client Profile","description":"Retrieve a client profile using the client ID.","operationId":"get_client_profile_api_v1_clients__client_id__get","parameters":[{"name":"client_id","in":"path","required":true,"schema":{"type":"string","title":"Client Id"}}],"responses":{"200":{"description":"Successful Response","content":{"application/json":{"schema":{"$ref":"#/components/schemas/app__clients__schemas__Client"}}}},"422":{"description":"Validation Error","content":{"application/json":{"schema":{"$ref":"#/components/schemas/HTTPValidationError"}}}}}}},"/api/v1/clients/search_by_phone/{phone_number}":{"get":{"tags":["Clients"],"summary":"Search Client By Phone","description":"Retrieves client details based on phone number.","operationId":"search_client_by_phone_api_v1_clients_search_by_phone__phone_number__get","parameters":[{"name":"phone_number","in":"path","required":true,"schema":{"type":"integer","title":"Phone Number"}}],"responses":{"200":{"description":"Successful Response","content":{"application/json":{"schema":{"type":"array","items":{"$ref":"#/components/schemas/app__clients__schemas__Client"},"title":"Response Search Client By Phone Api V1 Clients Search By Phone  Phone Number  Get"}}}},"422":{"description":"Validation Error","content":{"application/json":{"schema":{"$ref":"#/components/schemas/HTTPValidationError"}}}}}}},"/api/v1/enrollments/":{"post":{"tags":["Enrollments"],"summary":"Create Enrollment","operationId":"create_enrollment_api_v1_enrollments__post","requestBody":{"content":{"application/json":{"schema":{"$ref":"#/components/schemas/EnrollmentCreate"}}},"required":true},"responses":{"200":{"description":"Successful Response","content":{"application/json":{"schema":{"items":{"$ref":"#/components/schemas/Enrollment"},"type":"array","title":"Response Create Enrollment Api V1 Enrollments  Post"}}}},"422":{"description":"Validation Error","content":{"application/json":{"schema":{"$ref":"#/components/schemas/HTTPValidationError"}}}}}}},"/api/v1/search/clients":{"get":{"tags":["Search"],"summary":"Search Clients","operationId":"search_clients_api_v1_search_clients_get","parameters":[{"name":"contact_number","in":"query","required":true,"schema":{"type":"string","description":"Contact number to search","title":"Contact Number"},"description":"Contact number to search"},{"name":"limit","in":"query","required":false,"schema":{"type":"integer","default":10,"title":"Limit"}},{"name":"offset","in":"query","required":false,"schema":{"type":"integer","default":0,"title":"Offset"}}],"responses":{"200":{"description":"Successful Response","content":{"application/json":{"schema":{"type":"array","items":{"$ref":"#/components/schemas/app__clients__schemas__Client"},"title":"Response Search Clients Api V1 Search Clients Get"}}}},"422":{"description":"Validation Error","content":{"application/json":{"schema":{"$ref":"#/components/schemas/HTTPValidationError"}}}}}}}},"components":{"schemas":{"ClientCreate":{"properties":{"first_name":{"type":"string","maxLength":50,"minLength":2,"title":"First Name","description":"Client's first name"},"last_name":{"type":"string","maxLength":50,"minLength":2,"title":"Last Name","description":"Client's last name"},"date_of_birth":{"type":"string","format":"date-time","title":"Date Of Birth","description":"Client's date of birth (YYYY-MM-DD)"},"gender":{"type":"string","title":"Gender","description":"Client's gender (e.g., Male, Female, Other)"},"contact_number":{"anyOf":[{"type":"string"},{"type":"null"}],"title":"Contact Number","description":"Client's contact phone number"}},"type":"object","required":["first_name","last_name","date_of_birth","gender"],"title":"ClientCreate"},"DoctorLogin":{"properties":{"email":{"type":"string","format":"email","title":"Email"},"password":{"type":"string","title":"Password"}},"type":"object","required":["email","password"],"title":"DoctorLogin"},"DoctorProfile":{"properties":{"id":{"type":"string","title":"Id"},"email":{"type":"string","format":"email","title":"Email"}},"type":"object","required":["id","email"],"title":"DoctorProfile"},"DoctorSignUp":{"properties":{"email":{"type":"string","format":"email","title":"Email"},"password":{"type":"string","title":"Password"}},"type":"object","required":["email","password"],"title":"DoctorSignUp"},"Enrollment":{"properties":{"client_id":{"type":"string","format":"uuid","title":"Client Id"},"program_id":{"type":"string","format":"uuid","title":"Program Id"},"id":{"type":"integer","title":"Id"},"client":{"$ref":"#/components/schemas/app__clients__models__Client"},"program":{"$ref":"#/components/schemas/app__programs__models__Program"}},"type":"object","required":["client_id","program_id","id","client","program"],"title":"Enrollment"},"EnrollmentCreate":{"properties":{"client_id":{"type":"string","format":"uuid","title":"Client Id"},"program_ids":{"items":{"type":"string","format":"uuid"},"type":"array","title":"Program Ids"}},"type":"object","required":["client_id","program_ids"],"title":"EnrollmentCreate"},"HTTPValidationError":{"properties":{"detail":{"items":{"$ref":"#/components/schemas/ValidationError"},"type":"array","title":"Detail"}},"type":"object","title":"HTTPValidationError"},"ProgramBase":{"properties":{"program_name":{"type":"string","title":"Program Name"},"description":{"anyOf":[{"type":"string"},{"type":"null"}],"title":"Description"}},"type":"object","required":["program_name"],"title":"ProgramBase"},"ProgramCreate":{"properties":{"program_name":{"type":"string","title":"Program Name"},"description":{"anyOf":[{"type":"string"},{"type":"null"}],"title":"Description"}},"type":"object","required":["program_name"],"title":"ProgramCreate"},"TokenResponse":{"properties":{"access_token":{"type":"string","title":"Access Token"},"token_type":{"type":"string","title":"Token Type","default":"bearer"}},"type":"object","required":["access_token"],"title":"TokenResponse"},"ValidationError":{"properties":{"loc":{"items":{"anyOf":[{"type":"string"},{"type":"integer"}]},"type":"array","title":"Location"},"msg":{"type":"string","title":"Message"},"type":{"type":"string","title":"Error Type"}},"type":"object","required":["loc","msg","type"],"title":"ValidationError"},"app__clients__models__Client":{"properties":{"first_name":{"type":"string","maxLength":50,"minLength":2,"title":"First Name"},"last_name":{"type":"string","maxLength":50,"minLength":2,"title":"Last Name"},"date_of_birth":{"type":"string","format":"date-time","title":"Date Of Birth"},"gender":{"type":"string","title":"Gender"},"contact_number":{"anyOf":[{"type":"string"},{"type":"null"}],"title":"Contact Number"},"id":{"type":"string","title":"Id"},"created_at":{"type":"string","format":"date-time","title":"Created At"}},"type":"object","required":["first_name","last_name","date_of_birth","gender","id","created_at"],"title":"Client"},"app__clients__schemas__Client":{"properties":{"first_name":{"type":"string","maxLength":50,"minLength":2,"title":"First Name","description":"Client's first name"},"last_name":{"type":"string","maxLength":50,"minLength":2,"title":"Last Name","description":"Client's last name"},"date_of_birth":{"type":"string","format":"date-time","title":"Date Of Birth","description":"Client's date of birth (YYYY-MM-DD)"},"gender":{"type":"string","title":"Gender","description":"Client's gender (e.g., Male, Female, Other)"},"contact_number":{"anyOf":[{"type":"string"},{"type":"null"}],"title":"Contact Number","description":"Client's contact phone number"},"id":{"type":"string","title":"Id","description":"Unique identifier of the client"},"created_at":{"type":"string","format":"date-time","title":"Created At","description":"Timestamp when the client was registered"},"programs":{"items":{"$ref":"#/components/schemas/ProgramBase"},"type":"array","title":"Programs","default":[]}},"type":"object","required":["first_name","last_name","date_of_birth","gender","id","created_at"],"title":"Client"},"app__programs__models__Program":{"properties":{"program_name":{"type":"string","maxLength":100,"minLength":3,"title":"Program Name","description":"Name of the health program"},"description":{"anyOf":[{"type":"string","maxLength":500},{"type":"null"}],"title":"Description","description":"Optional description of the program"},"id":{"type":"string","title":"Id","description":"Unique identifier of the program"},"created_at":{"type":"string","format":"date-time","title":"Created At","description":"Timestamp when the program was created"}},"type":"object","required":["program_name","id","created_at"],"title":"Program"},"app__programs__schemas__Program":{"properties":{"program_name":{"type":"string","title":"Program Name"},"description":{"anyOf":[{"type":"string"},{"type":"null"}],"title":"Description"},"id":{"type":"string","title":"Id"},"created_at":{"type":"string","format":"date-time","title":"Created At"}},"type":"object","required":["program_name","id","created_at"],"title":"Program"}}}}